inmanta_plugins/apache/__init__.py
inmanta_plugins/apache/setup.cfg
inmanta_plugins/apache/model/_init.cf
inmanta_plugins/apache/templates/conf.tmpl
inmanta_plugins/apache/templates/sysconfig.tmpl
inmanta_plugins/apache/templates/vhost.tmpl
inmanta_module_apache-0.5.8.dist-info/METADATA
inmanta_module_apache-0.5.8.dist-info/WHEEL
inmanta_module_apache-0.5.8.dist-info/top_level.txt
inmanta_module_apache-0.5.8.dist-info/RECORD
