Metadata-Version: 2.1
Name: inmanta-module-apache
Version: 0.5.8
License: Apache 2.0
Requires-Dist: inmanta-module-std
Requires-Dist: inmanta-module-web
